babyvec/__init__.py
babyvec/_http_impl.py
babyvec/common.py
babyvec/faiss_db.py
babyvec/httpserver.py
babyvec/models.py
babyvec/py.typed
babyvec/chunker/__init__.py
babyvec/chunker/abstract_chunker.py
babyvec/chunker/rolling_sentence_window_chunker.py
babyvec/chunker/rolling_window_chunker.py
babyvec/computer/__init__.py
babyvec/computer/abstract_embedding_computer.py
babyvec/computer/embedding_computer_jina_bert.py
babyvec/computer/parallelized_embedding_computer.py
babyvec/embed_provider/__init__.py
babyvec/embed_provider/cached_embed_provider.py
babyvec/embed_provider/parallelized_cached_embed_provider.py
babyvec/index/__init__.py
babyvec/index/abstract_index.py
babyvec/index/abstract_index_factory.py
babyvec/index/faiss_index.py
babyvec/index/numpy_faiss_index_factory.py
babyvec/lib/__init__.py
babyvec/lib/sqlitedb.py
babyvec/store/__init__.py
babyvec/store/abstract_embedding_store.py
babyvec/store/abstract_metadata_store.py
babyvec/store/embedding_store_numpy.py
babyvec/store/metadata_store_sqlite.py
babyvec/store/__test__/__init__.py
babyvec/store/__test__/embedding_store_numpy_test.py
babyvec-0.2.1.dist-info/METADATA
babyvec-0.2.1.dist-info/WHEEL
babyvec-0.2.1.dist-info/top_level.txt
babyvec-0.2.1.dist-info/RECORD
