Metadata-Version: 2.1
Name: babyvec
Version: 0.2.1
Summary: Natural language embedding tools
Home-page: https://github.com/lummm/babyvec
Author: Liam Tengelis
Author-email: liam@blacktuskdata.com
Requires-Dist: certifi ==2024.6.2
Requires-Dist: charset-normalizer ==3.3.2
Requires-Dist: click ==8.1.7
Requires-Dist: faiss-cpu ==1.8.0
Requires-Dist: filelock ==3.15.3
Requires-Dist: fsspec ==2024.6.0
Requires-Dist: huggingface-hub ==0.23.4
Requires-Dist: idna ==3.7
Requires-Dist: jinja2 ==3.1.4
Requires-Dist: joblib ==1.4.2
Requires-Dist: markupsafe ==2.1.5
Requires-Dist: mpmath ==1.3.0
Requires-Dist: networkx ==3.3
Requires-Dist: nltk ==3.8.1
Requires-Dist: npy-append-array ==0.9.16
Requires-Dist: numpy ==1.26.4
Requires-Dist: packaging ==24.1
Requires-Dist: pyyaml ==6.0.1
Requires-Dist: regex ==2024.5.15
Requires-Dist: requests ==2.32.3
Requires-Dist: safetensors ==0.4.3
Requires-Dist: sympy ==1.12.1
Requires-Dist: tokenizers ==0.19.1
Requires-Dist: torch ==2.3.1
Requires-Dist: tqdm ==4.66.4
Requires-Dist: transformers ==4.41.2
Requires-Dist: typing-extensions ==4.12.2
Requires-Dist: urllib3 ==2.2.2
Provides-Extra: http
Requires-Dist: uvicorn ; extra == 'http'
Requires-Dist: fastapi ; extra == 'http'
Requires-Dist: pydantic ; extra == 'http'
